hostile/__init__.py
hostile/aligner.py
hostile/cli.py
hostile/lib.py
hostile/util.py
hostile-2.0.2.dist-info/entry_points.txt
hostile-2.0.2.dist-info/licenses/LICENSE
hostile-2.0.2.dist-info/WHEEL
hostile-2.0.2.dist-info/METADATA
hostile-2.0.2.dist-info/RECORD
