Metadata-Version: 2.4
Name: hostile
Version: 2.0.2
Summary: Accurate host read removal
Author-email: Bede Constantinides <b@bede.im>
Requires-Python: >=3.10
Classifier: License :: OSI Approved :: MIT License
License-File: LICENSE
Requires-Dist: defopt>=7.0.0
Requires-Dist: dnaio>=1.2.0
Requires-Dist: httpx>=0.24.1
Requires-Dist: platformdirs>=3.5.1
Requires-Dist: tqdm>=4.65.0
Requires-Dist: pytest>=7.3.1 ; extra == "dev"
Requires-Dist: pre-commit>=3.3.2 ; extra == "dev"
Requires-Dist: flit>=3.9.0 ; extra == "dev"
Project-URL: Home, https://github.com/bede/hostile
Provides-Extra: dev
